mcp_server_sensory/__init__.py
mcp_server_sensory/server.py
mcp_server_sensory/decoders/__init__.py
mcp_server_sensory/decoders/sstv.py
mcp_server_sensory/encoders/__init__.py
mcp_server_sensory/encoders/braille.py
mcp_server_sensory/encoders/morse.py
mcp_server_sensory/encoders/sstv.py
mcp_server_sensory-0.3.1.dist-info/METADATA
mcp_server_sensory-0.3.1.dist-info/WHEEL
mcp_server_sensory-0.3.1.dist-info/entry_points.txt
mcp_server_sensory-0.3.1.dist-info/RECORD
