Metadata-Version: 2.4
Name: mcp-server-sensory
Version: 0.3.1
Summary: Multi-Sensory AI Communication - Morse, Braille, SSTV/REFLUX encode+decode for off-grid AI networks. Complete sensory loop!
Project-URL: Homepage, https://humotica.com
Project-URL: Documentation, https://github.com/Humotica/mcp-server-sensory
Project-URL: Repository, https://github.com/Humotica/mcp-server-sensory
Author-email: Jasper van de Meent <jasper@humotica.com>, Root AI <root_ai@humotica.nl>
License-Expression: AGPL-3.0-or-later
Keywords: ai-communication,braille,ggwave,humotica,mcmurdo,mcp,morse,multimodal,off-grid,reflux,robot36,sensory,sstv
Classifier: Development Status :: 3 - Alpha
Classifier: Intended Audience :: Developers
Classifier: License :: OSI Approved :: GNU Affero General Public License v3 or later (AGPLv3+)
Classifier: Programming Language :: Python :: 3
Classifier: Programming Language :: Python :: 3.10
Classifier: Programming Language :: Python :: 3.11
Classifier: Programming Language :: Python :: 3.12
Classifier: Topic :: Communications
Classifier: Topic :: Communications :: Ham Radio
Classifier: Topic :: Scientific/Engineering :: Artificial Intelligence
Requires-Python: >=3.10
Requires-Dist: mcp>=1.0.0
Requires-Dist: numpy>=1.24.0
Requires-Dist: pillow>=10.0.0
Requires-Dist: pysstv>=0.5.0
Provides-Extra: audio
Requires-Dist: scipy>=1.11.0; extra == 'audio'
Requires-Dist: sounddevice>=0.4.6; extra == 'audio'
Provides-Extra: full
Requires-Dist: scipy>=1.11.0; extra == 'full'
Requires-Dist: sounddevice>=0.4.6; extra == 'full'
